qtheme/__init__.py
qtheme/main.py
qtheme/cli/__init__.py
qtheme/cli/kitty.py
qtheme/cli/menu.py
qtheme/cli/qtile.py
qtheme/utils/__init__.py
qtheme/utils/colors.py
qtheme-2.0.6.dist-info/LICENSE
qtheme-2.0.6.dist-info/METADATA
qtheme-2.0.6.dist-info/WHEEL
qtheme-2.0.6.dist-info/entry_points.txt
qtheme-2.0.6.dist-info/top_level.txt
qtheme-2.0.6.dist-info/RECORD
