Metadata-Version: 2.2
Name: qtheme
Version: 2.0.6
Summary: Tools for management qtile environment
Home-page: https://github.com/loadept/qtheme
Author: Jesus Machaca
Author-email: falcorgd@gmail.com
License: MIT
Classifier: Programming Language :: Python :: 3
Classifier: License :: OSI Approved :: MIT License
Classifier: Operating System :: POSIX :: Linux
Classifier: Topic :: Terminals :: Terminal Emulators/X Terminals
License-File: LICENSE
Dynamic: author
Dynamic: author-email
Dynamic: classifier
Dynamic: description
Dynamic: description-content-type
Dynamic: home-page
Dynamic: license
Dynamic: summary
